[
  {
    "question": "Why is LNMIIT considered a leading institute for Computer Science?",
    "choice1": "Highly qualified faculty and research environment",
    "choice2": "Student-led innovation and coding culture",
    "choice3": "Strong placement statistics",
    "choice4": "All of the above",
    "answer": 4
  },
  {
    "question": "Which of the following is LNMIIT’s annual cultural fest?",
    "choice1": "Plinth",
    "choice2": "Desportivos",
    "choice3": "Vivacity",
    "choice4": "Technika",
    "answer": 3
  },
  {
    "question": "Which fest at LNMIIT focuses on technical innovation and competitions?",
    "choice1": "Plinth",
    "choice2": "Vivacity",
    "choice3": "Desportivos",
    "choice4": "Eureka",
    "answer": 1
  },
  {
    "question": "Who is the current Director of LNMIIT (as of 2024)?",
    "choice1": "Dr. Rahul Banerjee",
    "choice2": "Prof. Sandeep Saini",
    "choice3": "Dr. Poonam Gera",
    "choice4": "Dr. Anurag Bhatnagar",
    "answer": 1
  },
  {
    "question": "What is the primary function of the Centre for Career Development (CCD) at LNMIIT?",
    "choice1": "Organizing cultural events",
    "choice2": "Managing campus placements and internships",
    "choice3": "Student counselling and wellness",
    "choice4": "Handling hostel management",
    "answer": 2
  },
  {
    "question": "How many academic departments does LNMIIT have?",
    "choice1": "Three",
    "choice2": "Four",
    "choice3": "Five",
    "choice4": "Six",
    "answer": 2
  },
  {
    "question": "Which student body coordinates club activities and events at LNMIIT?",
    "choice1": "Academic Council",
    "choice2": "Student Gymkhana",
    "choice3": "Cultural Affairs Committee",
    "choice4": "Plinth Council",
    "answer": 2
  },
  {
    "question": "What facilities are provided in LNMIIT hostels?",
    "choice1": "Wi-Fi, laundry, and reading rooms",
    "choice2": "AC rooms for all students",
    "choice3": "Gaming consoles",
    "choice4": "None of the above",
    "answer": 1
  },
  {
    "question": "Which department handles student counselling and mental wellness?",
    "choice1": "Health Centre",
    "choice2": "Student Gymkhana",
    "choice3": "Wellness Cell",
    "choice4": "CCD",
    "answer": 3
  },
  {
    "question": "Which club at LNMIIT is associated with street theatre performances?",
    "choice1": "Rendition",
    "choice2": "Aveg",
    "choice3": "Kronos",
    "choice4": "TechKnights",
    "answer": 2
  },
  {
    "question": "What is the role of the Institute Innovation Council (IIC) at LNMIIT?",
    "choice1": "To promote entrepreneurship and innovation",
    "choice2": "To manage hostel rules",
    "choice3": "To organize annual sports meets",
    "choice4": "To manage admissions",
    "answer": 1
  },
  {
    "question": "What is 'Desportivos' known for at LNMIIT?",
    "choice1": "Annual literary event",
    "choice2": "Cultural music fest",
    "choice3": "Annual sports festival",
    "choice4": "Tech hackathon",
    "answer": 3
  },
  {
    "question": "What services are offered at LNMIIT’s Central Library?",
    "choice1": "Book borrowing and reading space",
    "choice2": "Digital library and research access",
    "choice3": "Study rooms and printing facility",
    "choice4": "All of the above",
    "answer": 4
  },
  {
    "question": "Which programming club is known for coding competitions and mentorship?",
    "choice1": "TechKnights",
    "choice2": "LnmiCoder",
    "choice3": "Bytecrunch",
    "choice4": "CodeLoop",
    "answer": 2
  },
  {
    "question": "What is the first step in resolving academic grievances at LNMIIT?",
    "choice1": "Contacting the Dean of Academics directly",
    "choice2": "Speaking to the course instructor or faculty advisor",
    "choice3": "Filing a complaint on the LNMIIT portal",
    "choice4": "Discussing with peers and resolving informally",
    "answer": 2
  }
]
